brieftgbot/__init__.py
brieftgbot/brieftgbot.py
brief_telegram_bot-0.0.6.dist-info/METADATA
brief_telegram_bot-0.0.6.dist-info/WHEEL
brief_telegram_bot-0.0.6.dist-info/top_level.txt
brief_telegram_bot-0.0.6.dist-info/RECORD
