Metadata-Version: 2.1
Name: brief-telegram-bot
Version: 0.0.6
Summary: Telegram bot in brief.
Home-page: https://github.com/Brief-rf/brief-telegram-bot
Author: Brief
Author-email: brf2053@gmail.com
License: UNKNOWN
Platform: UNKNOWN
Classifier: Programming Language :: Python :: 3
Classifier: License :: OSI Approved :: MIT License
Classifier: Operating System :: OS Independent
Requires-Dist: requests
